README.md
setup.py
bin/task-run
ct_tasker.egg-info/PKG-INFO
ct_tasker.egg-info/SOURCES.txt
ct_tasker.egg-info/dependency_links.txt
ct_tasker.egg-info/not-zip-safe
ct_tasker.egg-info/top_level.txt
tasker/__init__.py
tasker/task.py