Metadata-Version: 1.0
Name: ct-tasker
Version: 0.1
Summary: Creative Tools interview exercise
Home-page: http://gitlab.com/OldIronHorse/tasker
Author: Simon Redding
Author-email: s1m0n.r3dd1ng@gmail.com
License: GPL3
Platform: UNKNOWN
